{
  "legs": [
    {"Exercise": "squats","Descriptions": "With a barbell on your upper back, move your legs and glutes downward as if sitting down in a chair and then stand back up. Make sure your knees don’t go past your toes and keep your back straight.", "Secondary": "Triceps", "link": "legs.htm"},
      
	{"Exercise": "lunges","Descriptions": "1) lay on the bench 2) press the desired weight", "Secondary": "Triceps", "link": "legs.htm"},
      
	{"Exercise": "chestFlies","Descriptions": "1) lay on the bench 2) press the desired weight", "Secondary": "Deltoids", "link": "legs.htm"}
      
    ]
	
}